pyropust-0.2.0.dist-info/METADATA
pyropust-0.2.0.dist-info/WHEEL
pyropust-0.2.0.dist-info/licenses/LICENSE
pyropust/__init__.py
pyropust/__init__.pyi
pyropust/catch.py
pyropust/do.py
pyropust/py.typed
pyropust/pyropust_native.cpython-312-darwin.so
pyropust/pyropust_native.pyi
pyropust-0.2.0.dist-info/RECORD
