Metadata-Version: 2.4
Name: pyropust
Version: 0.2.0
Classifier: Development Status :: 3 - Alpha
Classifier: Intended Audience :: Developers
Classifier: License :: OSI Approved :: MIT License
Classifier: Programming Language :: Python :: 3
Classifier: Programming Language :: Python :: 3.12
Classifier: Programming Language :: Python :: 3.13
Classifier: Programming Language :: Python :: 3.14
Classifier: Programming Language :: Rust
Classifier: Typing :: Typed
Requires-Dist: maturin>=1.6 ; extra == 'dev'
Requires-Dist: mypy>=1.10 ; extra == 'dev'
Requires-Dist: pyright>=1.1.370 ; extra == 'dev'
Requires-Dist: pytest>=9.0.2 ; extra == 'dev'
Requires-Dist: ruff>=0.6 ; extra == 'dev'
Provides-Extra: dev
License-File: LICENSE
Summary: Rust Result/Option types exposed to Python with @do generator short-circuiting
Keywords: rust,result,option,error-handling,type-safety,pyo3
Author: K-dash
License: MIT
Requires-Python: >=3.12
Project-URL: Homepage, https://github.com/K-dash/pyropust
Project-URL: Repository, https://github.com/K-dash/pyropust
Project-URL: Issues, https://github.com/K-dash/pyropust/issues
